{
  "input": "data\\jap_imgs_tech\\otsu\\pg_6.png",
  "lang": "en",
  "polys": [
    [
      [
        853,
        55
      ],
      [
        981,
        55
      ],
      [
        981,
        191
      ],
      [
        853,
        191
      ]
    ],
    [
      [
        846,
        915
      ],
      [
        965,
        915
      ],
      [
        965,
        1111
      ],
      [
        846,
        1111
      ]
    ],
    [
      [
        825,
        677
      ],
      [
        969,
        677
      ],
      [
        969,
        857
      ],
      [
        825,
        857
      ]
    ],
    [
      [
        817,
        1226
      ],
      [
        928,
        1226
      ],
      [
        928,
        1344
      ],
      [
        817,
        1344
      ]
    ],
    [
      [
        684,
        82
      ],
      [
        797,
        82
      ],
      [
        797,
        229
      ],
      [
        684,
        229
      ]
    ],
    [
      [
        650,
        1377
      ],
      [
        734,
        1377
      ],
      [
        734,
        1507
      ],
      [
        650,
        1507
      ]
    ],
    [
      [
        562,
        1224
      ],
      [
        672,
        1224
      ],
      [
        672,
        1337
      ],
      [
        562,
        1337
      ]
    ],
    [
      [
        551,
        102
      ],
      [
        633,
        102
      ],
      [
        633,
        249
      ],
      [
        551,
        249
      ]
    ],
    [
      [
        509,
        263
      ],
      [
        559,
        263
      ],
      [
        559,
        340
      ],
      [
        509,
        340
      ]
    ],
    [
      [
        400,
        1263
      ],
      [
        492,
        1263
      ],
      [
        492,
        1495
      ],
      [
        400,
        1495
      ]
    ],
    [
      [
        328,
        135
      ],
      [
        476,
        135
      ],
      [
        476,
        259
      ],
      [
        328,
        259
      ]
    ],
    [
      [
        215,
        689
      ],
      [
        351,
        689
      ],
      [
        351,
        878
      ],
      [
        215,
        878
      ]
    ],
    [
      [
        177,
        165
      ],
      [
        286,
        165
      ],
      [
        286,
        285
      ],
      [
        177,
        285
      ]
    ],
    [
      [
        83,
        692
      ],
      [
        161,
        692
      ],
      [
        161,
        878
      ],
      [
        83,
        878
      ]
    ],
    [
      [
        62,
        154
      ],
      [
        146,
        154
      ],
      [
        146,
        333
      ],
      [
        62,
        333
      ]
    ],
    [
      [
        45,
        1453
      ],
      [
        128,
        1453
      ],
      [
        128,
        1593
      ],
      [
        45,
        1593
      ]
    ],
    [
      [
        150,
        331
      ],
      [
        303,
        331
      ],
      [
        303,
        388
      ],
      [
        150,
        388
      ]
    ],
    [
      [
        0,
        1192
      ],
      [
        402,
        1192
      ],
      [
        402,
        1295
      ],
      [
        0,
        1295
      ]
    ]
  ],
  "texts": [
    "Hey, hey, hey, hey, hey, hey, hey, hey, hey, hey, hey, hey, hey, hey, hey, hey, hey, hey.",
    "At least I'll think about it when I'm old.",
    "You’re too young, you’re too young.",
    "Drink some of the juice from the tea.",
    "You can take him out once you're done with him.",
    "it's just a matter of time.",
    "Oh, my God! Thank you!",
    "I feel the same way.",
    "The first is the \"Fire\".",
    "Come on, kid, fuck you!",
    "Instead, the female or the boat will be lowered.",
    "I'll tell you what I'm talking about!",
    "Let's finish the conversation and have a drink.",
    "I am not a child!",
    "It doesn’t taste!",
    "Come on, you guys!",
    "The most common is the",
    "The first is the \"B\""
  ],
  "scores": [
    0.6737587849299113,
    0.9176243344942728,
    0.6767055198550225,
    0.924541691939036,
    0.8579026063283285,
    0.1826467514038086,
    0.9611376722653707,
    0.9304398000240326,
    0.9123323559761047,
    0.9709942042827606,
    0.7867100685834885,
    0.8887352347373962,
    0.893967847029368,
    0.9085436761379242,
    0.7412561178207397,
    0.881432056427002,
    0.8111721873283386,
    0.6074443459510803
  ],
  "best_model": [
    "hl",
    "hl",
    "fb",
    "nllb",
    "hl",
    "hl",
    "hl",
    "nllb",
    "nllb",
    "hl",
    "nllb",
    "hl",
    "nllb",
    "fb",
    "fb",
    "nllb",
    "nllb",
    "nllb"
  ],
  "best_model_score": [
    0.6737587849299113,
    0.9176243344942728,
    0.6767055198550225,
    0.924541691939036,
    0.8579026063283285,
    0.1826467514038086,
    0.9611376722653707,
    0.9304398000240326,
    0.9123323559761047,
    0.9709942042827606,
    0.7867100685834885,
    0.8887352347373962,
    0.893967847029368,
    0.9085436761379242,
    0.7412561178207397,
    0.881432056427002,
    0.8111721873283386,
    0.6074443459510803
  ],
  "source_texts": [
    "おいいじやねか",
    "せめてあと歳年とったち考えてやるよ",
    "一要するに元お前はガキすぎるんだ[一元]",
    "おこるなジュースでも飲め",
    "一度くちい連れてってやっても",
    "红",
    "うわ!ありがとう!",
    "おれもそう思うぜ",
    "おお",
    "ほらガキだおもしれえ!",
    "じやあかわりに雌か船を下りろ",
    "このケチシャンクスめ!言わせておけば!",
    "さあ話は終わりた飲もう",
    "おれはガキじゃないつ!!",
    "味じやないのかよ!",
    "きたねえぞ!",
    "がはははは",
    "たははばは"
  ],
  "base_ocr_scores": [
    0.6737587849299113,
    0.9176243344942728,
    0.6767055198550225,
    0.924541691939036,
    0.8579026063283285,
    0.1826467514038086,
    0.9611376722653707,
    0.9304398000240326,
    0.9123323559761047,
    0.9709942042827606,
    0.7867100685834885,
    0.8887352347373962,
    0.893967847029368,
    0.9085436761379242,
    0.7412561178207397,
    0.881432056427002,
    0.8111721873283386,
    0.6074443459510803
  ],
  "selection_debug": [
    {
      "model": "hl",
      "text": "Hey, hey, hey, hey, hey, hey, hey, hey, hey, hey, hey, hey, hey, hey, hey, hey, hey, hey.",
      "score": 0.6737587849299113,
      "is_english": true,
      "en_ratio": 1.0,
      "reason": "best_english_highest_score"
    },
    {
      "model": "hl",
      "text": "At least I'll think about it when I'm old.",
      "score": 0.9176243344942728,
      "is_english": true,
      "en_ratio": 1.0,
      "reason": "best_english_highest_score"
    },
    {
      "model": "fb",
      "text": "You’re too young, you’re too young.",
      "score": 0.6767055198550225,
      "is_english": true,
      "en_ratio": 1.0,
      "reason": "best_english_highest_score"
    },
    {
      "model": "nllb",
      "text": "Drink some of the juice from the tea.",
      "score": 0.924541691939036,
      "is_english": true,
      "en_ratio": 1.0,
      "reason": "best_english_highest_score"
    },
    {
      "model": "hl",
      "text": "You can take him out once you're done with him.",
      "score": 0.8579026063283285,
      "is_english": true,
      "en_ratio": 1.0,
      "reason": "best_english_highest_score"
    },
    {
      "model": "hl",
      "text": "it's just a matter of time.",
      "score": 0.1826467514038086,
      "is_english": true,
      "en_ratio": 1.0,
      "reason": "best_english_highest_score"
    },
    {
      "model": "hl",
      "text": "Oh, my God! Thank you!",
      "score": 0.9611376722653707,
      "is_english": true,
      "en_ratio": 1.0,
      "reason": "best_english_highest_score"
    },
    {
      "model": "nllb",
      "text": "I feel the same way.",
      "score": 0.9304398000240326,
      "is_english": true,
      "en_ratio": 1.0,
      "reason": "best_english_highest_score"
    },
    {
      "model": "nllb",
      "text": "The first is the \"Fire\".",
      "score": 0.9123323559761047,
      "is_english": true,
      "en_ratio": 1.0,
      "reason": "best_english_highest_score"
    },
    {
      "model": "hl",
      "text": "Come on, kid, fuck you!",
      "score": 0.9709942042827606,
      "is_english": true,
      "en_ratio": 1.0,
      "reason": "best_english_highest_score"
    },
    {
      "model": "nllb",
      "text": "Instead, the female or the boat will be lowered.",
      "score": 0.7867100685834885,
      "is_english": true,
      "en_ratio": 1.0,
      "reason": "best_english_highest_score"
    },
    {
      "model": "hl",
      "text": "I'll tell you what I'm talking about!",
      "score": 0.8887352347373962,
      "is_english": true,
      "en_ratio": 1.0,
      "reason": "best_english_highest_score"
    },
    {
      "model": "nllb",
      "text": "Let's finish the conversation and have a drink.",
      "score": 0.893967847029368,
      "is_english": true,
      "en_ratio": 1.0,
      "reason": "best_english_highest_score"
    },
    {
      "model": "fb",
      "text": "I am not a child!",
      "score": 0.9085436761379242,
      "is_english": true,
      "en_ratio": 1.0,
      "reason": "best_english_highest_score"
    },
    {
      "model": "fb",
      "text": "It doesn’t taste!",
      "score": 0.7412561178207397,
      "is_english": true,
      "en_ratio": 1.0,
      "reason": "best_english_highest_score"
    },
    {
      "model": "nllb",
      "text": "Come on, you guys!",
      "score": 0.881432056427002,
      "is_english": true,
      "en_ratio": 1.0,
      "reason": "best_english_highest_score"
    },
    {
      "model": "nllb",
      "text": "The most common is the",
      "score": 0.8111721873283386,
      "is_english": true,
      "en_ratio": 1.0,
      "reason": "best_english_highest_score"
    },
    {
      "model": "nllb",
      "text": "The first is the \"B\"",
      "score": 0.6074443459510803,
      "is_english": true,
      "en_ratio": 1.0,
      "reason": "best_english_highest_score"
    }
  ],
  "sources": {
    "base_json": "outputs\\jap_ocr_otsu\\json\\pg_6.json",
    "fb_json": "outputs\\jap_ocr_otsu\\translation_fb\\pg_6.json",
    "hl_json": "outputs\\jap_ocr_otsu\\translation_hl\\pg_6.json",
    "nllb_json": "outputs\\jap_ocr_otsu\\translation_nllb\\pg_6.json"
  }
}