{
  "input": "outputs\\jap\\adaptive\\pg_49.png",
  "lang": "en",
  "polys": [
    [
      [
        728,
        1158
      ],
      [
        789,
        1158
      ],
      [
        789,
        1298
      ],
      [
        728,
        1298
      ]
    ],
    [
      [
        688,
        657
      ],
      [
        772,
        657
      ],
      [
        772,
        774
      ],
      [
        688,
        774
      ]
    ],
    [
      [
        286,
        1148
      ],
      [
        359,
        1148
      ],
      [
        359,
        1300
      ],
      [
        286,
        1300
      ]
    ],
    [
      [
        -1,
        959
      ],
      [
        76,
        959
      ],
      [
        76,
        1083
      ],
      [
        -1,
        1083
      ]
    ]
  ],
  "texts": [
    "colleagues 集",
    "Did you know that fish?",
    "People want to be able to do that.",
    "And the flag of the pirates."
  ],
  "scores": [
    0.8658959865570068,
    0.8217895328998566,
    0.9087598919868469,
    0.9693581163883209
  ],
  "source_texts": [
    "仲間集",
    "知ったか魚め",
    "人はほしいなア",
    "そして海賊旗"
  ]
}